[
  { "name": "Vineet Khandelwal" },
  { "name": "Vivek Dwivedi" },
  { "name": "Ashish Goel" },
  { "name": "Vijay Khare" },
  { "name": "Jasmine Saini" },
  { "name": "Alok Joshi" },
  { "name": "Megha Agarwal" },
  { "name": "Richa Gupta" },
  { "name": "Madhu Jain" },
  { "name": "Shamim Akhter" },
  { "name": "Pankaj Kumar Yadav" },
  { "name": "Kapil Dev Tyagi" },
  { "name": "Garima Kapur" },
  { "name": "Rahul Kaushik" },
  { "name": "Satyendra Kumar" },
  { "name": "Archana Pandey" },
  { "name": "Ashish Gupta" },
  { "name": "Kuldeep Baderia" },
  { "name": "Bajrang Bansal" },
  { "name": "Vimal Kumar Mishra" },
  { "name": "Kaushal Nigam" },
  { "name": "Parul Arora" },
  { "name": "Reema Buddhiraja" },
  { "name": "Saurabh Chaturvedi" },
  { "name": "Gaurav Verma" },
  { "name": "Shruti Kalra" },
  { "name": "Atul Kumar" },
  { "name": "Hemant Kumar" },
  { "name": "Juhi Gupta" },
  { "name": "Abhishek Kashyap" },
  { "name": "Yogesh Kumar" },
  { "name": "Bhagirath Sahu" },
  { "name": "Rachna Singh" },
  { "name": "Neetu Joshi" },
  { "name": "Ajay Kumar" },
  { "name": "Akansha Bansal" },
  { "name": "Ruby Beniwal" },
  { "name": "Prabhakar jha" },
  { "name": "Gaurav Khanna" },
  { "name": "Samriti Kalia" },
  { "name": "Bhawna Gupta" },
  { "name": "Smriti Bhatnagar" },
  { "name": "Atul Kumar Srivastava" },
  { "name": "B. Suresh" },
  { "name": "Monika" },
  { "name": "Vinay Anand Tikkiwal" },
  { "name": "Priyanka Kwatra" },
  { "name": "Shradha Saxena" },
  { "name": "Vishal Narain Saxena" },
  { "name": "Ankur Bhardwaj" },
  { "name": "Shivaji Tyagi" },
  { "name": "Jyoti Vyas" },
  { "name": "Mandeep Narula" },
  { "name": "Ritesh Kumar Sharma" },
  { "name": "Varun Goel" },
  { "name": "Abhay Kumar" },
  { "name": "Raghvenda Kumar Singh" },
  { "name": "Madhu Jhariya" },
  { "name": "Nitesh Kumar" },
  { "name": "Rahul Kumar" },
  { "name": "Chandan Kumar" },
  { "name": "Nisha Venkatesh" },
  { "name": "" },
  {"name": ""}
]
